zai/__init__.py
zai/_client.py
zai/_version.py
zai/api_resource/__init__.py
zai/api_resource/agents/__init__.py
zai/api_resource/agents/agents.py
zai/api_resource/assistant/__init__.py
zai/api_resource/assistant/assistant.py
zai/api_resource/audio/__init__.py
zai/api_resource/audio/audio.py
zai/api_resource/audio/transcriptions.py
zai/api_resource/batch/__init__.py
zai/api_resource/batch/batches.py
zai/api_resource/chat/__init__.py
zai/api_resource/chat/async_completions.py
zai/api_resource/chat/chat.py
zai/api_resource/chat/completions.py
zai/api_resource/embeddings/__init__.py
zai/api_resource/embeddings/embeddings.py
zai/api_resource/file_parser/__init__.py
zai/api_resource/file_parser/file_parser.py
zai/api_resource/files/__init__.py
zai/api_resource/files/files.py
zai/api_resource/images/__init__.py
zai/api_resource/images/images.py
zai/api_resource/moderations/__init__.py
zai/api_resource/moderations/moderations.py
zai/api_resource/ocr/__init__.py
zai/api_resource/ocr/handwriting_ocr.py
zai/api_resource/tools/__init__.py
zai/api_resource/tools/tools.py
zai/api_resource/videos/__init__.py
zai/api_resource/videos/videos.py
zai/api_resource/voice/__init__.py
zai/api_resource/voice/voice.py
zai/api_resource/web_reader/__init__.py
zai/api_resource/web_reader/web_reader.py
zai/api_resource/web_search/__init__.py
zai/api_resource/web_search/web_search.py
zai/core/__init__.py
zai/core/_base_api.py
zai/core/_base_compat.py
zai/core/_base_models.py
zai/core/_base_type.py
zai/core/_constants.py
zai/core/_errors.py
zai/core/_files.py
zai/core/_http_client.py
zai/core/_json_encoder.py
zai/core/_jwt_token.py
zai/core/_legacy_binary_response.py
zai/core/_legacy_response.py
zai/core/_request_opt.py
zai/core/_response.py
zai/core/_streaming.py
zai/core/_utils/__init__.py
zai/core/_utils/_transform.py
zai/core/_utils/_typing.py
zai/core/_utils/_utils.py
zai/core/logs.py
zai/core/pagination.py
zai/py.typed
zai/types/__init__.py
zai/types/agents/__init__.py
zai_sdk-0.2.0.dist-info/LICENSE
zai_sdk-0.2.0.dist-info/METADATA
zai_sdk-0.2.0.dist-info/WHEEL
zai_sdk-0.2.0.dist-info/RECORD
