Metadata-Version: 2.1
Name: zai-sdk
Version: 0.2.0
Summary: A SDK library for accessing big model apis from Z.ai
Author: Z.ai
Requires-Python: >=3.8, !=2.7.*, !=3.0.*, !=3.1.*, !=3.2.*, !=3.3.*, !=3.4.*, !=3.5.*, !=3.6.*, !=3.7.*
Classifier: Programming Language :: Python :: 3
Classifier: Programming Language :: Python :: 3.8
Classifier: Programming Language :: Python :: 3.9
Classifier: Programming Language :: Python :: 3.10
Classifier: Programming Language :: Python :: 3.11
Classifier: Programming Language :: Python :: 3.12
Provides-Extra: cli
Provides-Extra: extended-testing
Requires-Dist: cachetools (>=4.2.2)
Requires-Dist: httpx (>=0.23.0)
Requires-Dist: pydantic (>=1.9.0,<3.0)
Requires-Dist: pydantic-core (>=2.14.6)
Requires-Dist: pyjwt (>=2.9.0,<3.0.0)
